axiomatic/__init__.py
axiomatic/base_client.py
axiomatic/client.py
axiomatic/code_execution/__init__.py
axiomatic/code_execution/client.py
axiomatic/code_execution/python/__init__.py
axiomatic/code_execution/python/client.py
axiomatic/core/__init__.py
axiomatic/core/api_error.py
axiomatic/core/client_wrapper.py
axiomatic/core/datetime_utils.py
axiomatic/core/file.py
axiomatic/core/http_client.py
axiomatic/core/jsonable_encoder.py
axiomatic/core/pydantic_utilities.py
axiomatic/core/query_encoder.py
axiomatic/core/remove_none_from_dict.py
axiomatic/core/request_options.py
axiomatic/core/serialization.py
axiomatic/digital_twin/__init__.py
axiomatic/digital_twin/client.py
axiomatic/document/__init__.py
axiomatic/document/client.py
axiomatic/document/expression/__init__.py
axiomatic/document/expression/client.py
axiomatic/document/plot/__init__.py
axiomatic/document/plot/client.py
axiomatic/document/plot/types/__init__.py
axiomatic/document/plot/types/plot_points_response.py
axiomatic/environment.py
axiomatic/errors/__init__.py
axiomatic/errors/unprocessable_entity_error.py
axiomatic/formalization/__init__.py
axiomatic/formalization/client.py
axiomatic/formalization/constraints/__init__.py
axiomatic/formalization/constraints/client.py
axiomatic/formalization/solution/__init__.py
axiomatic/formalization/solution/client.py
axiomatic/formalization/solution/types/__init__.py
axiomatic/formalization/solution/types/solution_body_values_value.py
axiomatic/fso/__init__.py
axiomatic/fso/client.py
axiomatic/fso/lens/__init__.py
axiomatic/fso/lens/client.py
axiomatic/lean/__init__.py
axiomatic/lean/client.py
axiomatic/lean/z3/__init__.py
axiomatic/lean/z3/client.py
axiomatic/magic.py
axiomatic/pic/__init__.py
axiomatic/pic/circuit/__init__.py
axiomatic/pic/circuit/client.py
axiomatic/pic/circuit/types/__init__.py
axiomatic/pic/circuit/types/settings.py
axiomatic/pic/circuit/types/statement.py
axiomatic/pic/client.py
axiomatic/pic/component/__init__.py
axiomatic-0.0.143.dist-info/METADATA
axiomatic-0.0.143.dist-info/WHEEL
axiomatic-0.0.143.dist-info/RECORD
