Metadata-Version: 2.1
Name: axiomatic
Version: 0.0.143
Summary: 
Requires-Python: >=3.8,<4.0
Classifier: Intended Audience :: Developers
Classifier: Operating System :: MacOS
Classifier: Operating System :: Microsoft :: Windows
Classifier: Operating System :: OS Independent
Classifier: Operating System :: POSIX
Classifier: Operating System :: POSIX :: Linux
Classifier: Programming Language :: Python
Classifier: Programming Language :: Python :: 3
Classifier: Programming Language :: Python :: 3.8
Classifier: Programming Language :: Python :: 3.9
Classifier: Programming Language :: Python :: 3.10
Classifier: Programming Language :: Python :: 3.11
Classifier: Programming Language :: Python :: 3.12
Classifier: Topic :: Software Development :: Libraries :: Python Modules
Classifier: Typing :: Typed
Requires-Dist: dill (>=0.3.4)
Requires-Dist: fastjsonschema (>=2.21.1)
Requires-Dist: httpx (>=0.21.2)
Requires-Dist: hypernetx (>=2.0.0)
Requires-Dist: ipywidgets (>=7.0.0)
Requires-Dist: pydantic (>=1.9.2)
Requires-Dist: pydantic-core (>=2.18.2,<3.0.0)
Requires-Dist: pyvis (>=0.1.2.0)
Requires-Dist: requests (>2.26.0)
Requires-Dist: types-requests (>2.0.0)
Requires-Dist: typing_extensions (>=4.0.0)
